eldam/__init__.py
eldam/settings.py
eldam/core/__init__.py
eldam/core/elda.py
eldam/core/elda_index.py
eldam/core/lci_data.py
eldam/core/parameters.py
eldam/core/simapro.py
eldam/gui/__init__.py
eldam/gui/dialogs.py
eldam/gui/exception_hook.py
eldam/gui/gui_parameters.py
eldam/gui/mainwindow.py
eldam/gui/widgets/__init__.py
eldam/gui/widgets/base_widgets.py
eldam/gui/widgets/blank_elda.py
eldam/gui/widgets/compare_simapro_export_with_elda.py
eldam/gui/widgets/copy_elda_metadata.py
eldam/gui/widgets/elda_to_simapro.py
eldam/gui/widgets/generate_elda_index.py
eldam/gui/widgets/simapro_to_elda.py
eldam/gui/widgets/update_elda_template.py
eldam/utils/__init__.py
eldam/utils/elda.py
eldam/utils/exceptions.py
eldam/utils/gui.py
eldam/utils/lci_data.py
eldam/utils/misc.py
eldam/utils/observer.py
eldam/utils/simapro.py
eldam/utils/styles.py
eldam/utils/xls.py
files/EldaIndex.xlsx
files/EldaTemplate.xlsm
files/icons/ELDAM.png
files/icons/about.png
files/icons/back.png
files/icons/blank_elda.png
files/icons/compare_simapro_excel.png
files/icons/continue.png
files/icons/copy_elda_metadata.png
files/icons/elsa.ico
files/icons/elsa_logo.png
files/icons/eu.png
files/icons/eu_occitanie.png
files/icons/excel2simapro.png
files/icons/exit.png
files/icons/generate_elda_index.png
files/icons/occitanie.png
files/icons/simapro2excel.png
files/icons/update_elda.png
files/templates/biosphere_flow_comment.jinja2
files/templates/simapro_csv_template.jinja2
files/templates/simple_comment.jinja2
files/templates/technosphere_flow_comment.jinja2
files/user_interfaces/about.ui
files/user_interfaces/blank_elda.ui
files/user_interfaces/compare_simapro_export_with_elda.ui
files/user_interfaces/copy_elda_metadata.ui
files/user_interfaces/elda_to_simapro.ui
files/user_interfaces/generate_elda_index.ui
files/user_interfaces/mainwindow.ui
files/user_interfaces/parameter_conflict_dialog.ui
files/user_interfaces/simapro_to_elda.ui
files/user_interfaces/update_elda_template.ui
tests/__init__.py
ELDAM_LCA-1.0.dist-info/LICENSE
ELDAM_LCA-1.0.dist-info/METADATA
ELDAM_LCA-1.0.dist-info/WHEEL
ELDAM_LCA-1.0.dist-info/top_level.txt
ELDAM_LCA-1.0.dist-info/RECORD
