Metadata-Version: 2.1
Name: ELDAM-LCA
Version: 1.0
Summary: Life Cycle Assessment data management
Home-page: https://framagit.org/GustaveCoste/eldam
Author: Gustave Coste
Author-email: gustave.coste@inrae.fr
License: UNKNOWN
Keywords: Life Cycle Assessment,Life Cycle Inventory,Data Quality
Platform: UNKNOWN
Classifier: Programming Language :: Python :: 3
Classifier: License :: OSI Approved :: GNU General Public License v3 (GPLv3)
Classifier: Operating System :: OS Independent
Requires-Python: >=3.6
Requires-Dist: jinja2
Requires-Dist: openpyxl
